[{"Name":"Стул","Description":"создание через редактор","Category_ID":2,"Creator_ID":0,"Count":5,"Prise":5,"Images":"C:\\Users\\u\\source\\repos\\SHOP\\bin\\Debug\\images\\1.jpg"},{"Name":"Название Три","Description":"описаниеТри","Category_ID":0,"Creator_ID":1,"Count":3,"Prise":5,"Images":"C:\\Users\\u\\source\\repos\\SHOP\\bin\\Debug\\images\\1.png"},{"Name":"Название Два","Description":"описаниеДва","Category_ID":1,"Creator_ID":0,"Count":3,"Prise":5,"Images":"C:\\Users\\u\\source\\repos\\SHOP\\bin\\Debug\\images\\AAA.png"},{"Name":"Каво","Description":"В России","Category_ID":2,"Creator_ID":2,"Count":1,"Prise":999,"Images":"C:\\Users\\u\\source\\repos\\SHOP\\bin\\Debug\\images\\цветы.jpg"},{"Name":"Шо","Description":"В дубае","Category_ID":2,"Creator_ID":2,"Count":3,"Prise":9,"Images":"C:\\Users\\u\\source\\repos\\SHOP\\bin\\Debug\\images\\dubai.png"},{"Name":"тест","Description":"тест","Category_ID":0,"Creator_ID":0,"Count":0,"Prise":0,"Images":"C:\\Users\\u\\source\\repos\\SHOP\\bin\\Debug\\images\\defolt.png"}]